<physvol name="entry_pipe_phy">
  <volumeref ref="entry_pipe_log" />
  <position x="0" y="laser_gap" z="-(212.43+65.12)*25.4-500"/>
</physvol>

<physvol name="exit_pipe_phy">
  <volumeref ref="exit_pipe_log" />
  <position x="0" y="laser_gap" z="(212.43+64.80)*25.4+500"/>
</physvol>

<physvol name="Filler">
  <volumeref ref="drift_pipe_log" />
  <positionref ref="chicane_position" />
</physvol>
<physvol name="drift_pipe2_phy">
  <volumeref ref="drift_pipe2_log" />
</physvol>

<physvol name="bend_pipe_1_phy">
  <volumeref ref="bend_pipe_1_log" />
  <position x="0" y="8.484*25.4/2" z="-(212.43+65.12)*25.4/2-800"/>
  <rotation unit="degree" x="-bend_angle" y="0" z="0"/>
</physvol>

<physvol name="bend_pipe_2_phy">
  <volumeref ref="bend_pipe_2_log" />
  <position x="0" y="8.484*25.4/2" z="(212.43+64.80)*25.4/2+800"/>
  <rotation unit="degree" x="bend_angle" y="0" z="0"/>
</physvol>

